CHANGES.md
CONTRIBUTORS.md
LICENSE
MANIFEST.in
README.md
setup.py
rawes/__init__.py
rawes/connection_pool.py
rawes/elastic.py
rawes/elastic_exception.py
rawes/encoders.py
rawes/http_connection.py
rawes/thrift_connection.py
rawes/utils.py
rawes.egg-info/PKG-INFO
rawes.egg-info/SOURCES.txt
rawes.egg-info/dependency_links.txt
rawes.egg-info/not-zip-safe
rawes.egg-info/requires.txt
rawes.egg-info/top_level.txt
rawes/thrift_elasticsearch/Rest.py
rawes/thrift_elasticsearch/__init__.py
rawes/thrift_elasticsearch/constants.py
rawes/thrift_elasticsearch/ttypes.py
tests/__init__.py
tests/config.py
tests/connection_pool_tests.py
tests/core_tests.py
tests/py3k.py
tests/test_encoder.py
tests/integration/__init__.py
tests/integration/connection_pool_integration_tests.py