Metadata-Version: 1.1
Name: rawes
Version: 0.5.5
Summary: rawes elasticsearch driver
Home-page: https://github.com/humangeo/rawes
Author: Dan Noble
Author-email: @dwnoble
License: Apache-2.0
Download-URL: https://github.com/humangeo/rawes/tarball/master
Platform: UNKNOWN
Classifier: Development Status :: 4 - Beta
Classifier: License :: OSI Approved :: Apache Software License
Classifier: Programming Language :: Python
Classifier: Topic :: Software Development :: Libraries :: Python Modules
